date_query/__init__.py
date_query/__main__.py
date_query/date_query.py
date_query-0.10.2.dist-info/DESCRIPTION.rst
date_query-0.10.2.dist-info/METADATA
date_query-0.10.2.dist-info/RECORD
date_query-0.10.2.dist-info/WHEEL
date_query-0.10.2.dist-info/entry_points.txt
date_query-0.10.2.dist-info/metadata.json
date_query-0.10.2.dist-info/top_level.txt
