Metadata-Version: 2.0
Name: date-query
Version: 0.10.2
Summary: A program to query dates
Home-page: https://github.com/sgambino/project-packaging
Author: Steve Gambino
Author-email: stevegambino@gmail.com
License: MIT
Keywords: date scheduling
Platform: UNKNOWN
Classifier: Development Status :: 3 - Alpha
Classifier: Intended Audience :: Developers
Classifier: Topic :: Software Development
Classifier: Topic :: Utilities
Classifier: License :: OSI Approved :: MIT License
Classifier: Programming Language :: Python :: 2
Classifier: Programming Language :: Python :: 2.7
